[
    {
        "model":"db_models.dayofweek",
        "pk":1,
        "fields":{
            "name":"Monday"
        }
    },
    {
        "model":"db_models.dayofweek",
        "pk":2,
        "fields":{
            "name":"Tuesday"
        }
    },
    {
        "model":"db_models.dayofweek",
        "pk":3,
        "fields":{
            "name":"Wednesday"
        }
    },
    {
        "model":"db_models.dayofweek",
        "pk":4,
        "fields":{
            "name":"Thursday"
        }
    },
    {
        "model":"db_models.dayofweek",
        "pk":5,
        "fields":{
            "name":"Friday"
        }
    },
    {
        "model":"db_models.dayofweek",
        "pk":6,
        "fields":{
            "name":"Saturday"
        }
    },
    {
        "model":"db_models.dayofweek",
        "pk":7,
        "fields":{
            "name":"Sunday"
        }
    }
]
